[{"library": "Central Library", "distance": 521857.06, "duration": 19332.9, "weight": 19513.31}, {"library": "Crownhill Library", "distance": 519058.13, "duration": 19234.82, "weight": 19415.21}, {"library": "Devonport Library", "distance": 522915.75, "duration": 19434.47, "weight": 19614.88}, {"library": "Efford Library", "distance": 518001.75, "duration": 19372.62, "weight": 19553.02}, {"library": "Estover Library", "distance": 518359.16, "duration": 19166.11, "weight": 19346.5}, {"library": "North Prospect Library", "distance": 521206.59, "duration": 19286.61, "weight": 19467.01}, {"library": "Peverell Library", "distance": 519424.63, "duration": 19133.15, "weight": 19313.54}, {"library": "Plympton Library", "distance": 512414.06, "duration": 18992.74, "weight": 19173.13}, {"library": "Plymstock Library", "distance": 519716.72, "duration": 19352, "weight": 19532.4}, {"library": "Southway Library", "distance": 523052.41, "duration": 19379.93, "weight": 19560.33}, {"library": "St Budeaux Library", "distance": 522855.59, "duration": 19229.45, "weight": 19409.84}, {"library": "West Park Library", "distance": 523046.91, "duration": 19275.36, "weight": 19455.75}]