[{"library": "Central Library", "distance": 1225871.25, "duration": 412402.19, "weight": 394881.78}, {"library": "Crownhill Library", "distance": 1230431.5, "duration": 415685.56, "weight": 397798.97}, {"library": "Devonport Library", "distance": 1226594.5, "duration": 412922.91, "weight": 395493.09}, {"library": "Efford Library", "distance": 1229259.38, "duration": 414841.59, "weight": 397032.94}, {"library": "Estover Library", "distance": 1232165.63, "duration": 416934.03, "weight": 398910.81}, {"library": "North Prospect Library", "distance": 1228130.38, "duration": 414028.75, "weight": 396476.69}, {"library": "Peverell Library", "distance": 1228486.38, "duration": 414285.06, "weight": 396483.13}, {"library": "Plympton Library", "distance": 610997.13, "duration": 434939.34, "weight": 398992.47}, {"library": "Plymstock Library", "distance": 1230130.25, "duration": 415468.63, "weight": 397875.31}, {"library": "Southway Library", "distance": 612056.19, "duration": 418050.88, "weight": 399509.66}, {"library": "St Budeaux Library", "distance": 1230147.25, "duration": 415480.84, "weight": 397680.16}, {"library": "West Park Library", "distance": 1230987.75, "duration": 416086, "weight": 398300.91}]