[{"library": "Central Library", "distance": 1206037.88, "duration": 405532.13, "weight": 380666.34}, {"library": "Crownhill Library", "distance": 1210598.25, "duration": 408815.5, "weight": 383583.53}, {"library": "Devonport Library", "distance": 1206761.13, "duration": 406052.84, "weight": 381277.69}, {"library": "Efford Library", "distance": 1209426, "duration": 407971.53, "weight": 382817.53}, {"library": "Estover Library", "distance": 1212332.25, "duration": 410063.97, "weight": 384695.41}, {"library": "North Prospect Library", "distance": 1208297, "duration": 407158.69, "weight": 382261.25}, {"library": "Peverell Library", "distance": 1208653, "duration": 407415, "weight": 382267.72}, {"library": "Plympton Library", "distance": 1213539.38, "duration": 410933.09, "weight": 385745.63}, {"library": "Plymstock Library", "distance": 1210296.88, "duration": 408598.56, "weight": 383659.88}, {"library": "Southway Library", "distance": 1213883.38, "duration": 411180.81, "weight": 385852.94}, {"library": "St Budeaux Library", "distance": 1210313.88, "duration": 408610.75, "weight": 383464.75}, {"library": "West Park Library", "distance": 1211154.38, "duration": 409215.94, "weight": 384085.5}]