[{"library": "Central Library", "distance": 618702.63, "duration": 22964.57, "weight": 22755.28}, {"library": "Crownhill Library", "distance": 615903.69, "duration": 22866.49, "weight": 22657.19}, {"library": "Devonport Library", "distance": 619761.31, "duration": 23066.14, "weight": 22856.86}, {"library": "Efford Library", "distance": 614847.31, "duration": 23004.29, "weight": 22794.99}, {"library": "Estover Library", "distance": 615204.75, "duration": 22797.78, "weight": 22588.47}, {"library": "North Prospect Library", "distance": 618052.19, "duration": 22918.28, "weight": 22708.98}, {"library": "Peverell Library", "distance": 616270.19, "duration": 22764.82, "weight": 22555.51}, {"library": "Plympton Library", "distance": 609259.63, "duration": 22624.41, "weight": 22415.1}, {"library": "Plymstock Library", "distance": 616562.31, "duration": 22983.67, "weight": 22774.37}, {"library": "Southway Library", "distance": 619897.94, "duration": 23011.6, "weight": 22802.3}, {"library": "St Budeaux Library", "distance": 619701.19, "duration": 22861.12, "weight": 22651.81}, {"library": "West Park Library", "distance": 619892.5, "duration": 22907.03, "weight": 22697.72}]