[{"library": "Central Library", "distance": 518217.66, "duration": 121452.88, "weight": 91110.38}, {"library": "Crownhill Library", "distance": 516559.22, "duration": 121244.52, "weight": 90940.68}, {"library": "Devonport Library", "distance": 520853.38, "duration": 121994.69, "weight": 91542.28}, {"library": "Efford Library", "distance": 515201.41, "duration": 121066.55, "weight": 90789.44}, {"library": "Estover Library", "distance": 515366.38, "duration": 121055.11, "weight": 90758.59}, {"library": "North Prospect Library", "distance": 518856.84, "duration": 121821.44, "weight": 91372.9}, {"library": "Peverell Library", "distance": 517085.91, "duration": 121486.16, "weight": 91096.79}, {"library": "Plympton Library", "distance": 509257.09, "duration": 119606.4, "weight": 89643.24}, {"library": "Plymstock Library", "distance": 512910.38, "duration": 120420.59, "weight": 90330.98}, {"library": "Southway Library", "distance": 519239.56, "duration": 122017.81, "weight": 91728.58}, {"library": "St Budeaux Library", "distance": 521324.06, "duration": 122144.27, "weight": 91642.45}, {"library": "West Park Library", "distance": 519020.78, "duration": 121689.14, "weight": 91285.72}]