[{"library": "Central Library", "distance": 398333, "duration": 91182.38, "weight": 73710.66}, {"library": "Crownhill Library", "distance": 411975.53, "duration": 93362.24, "weight": 73122.15}, {"library": "Devonport Library", "distance": 401221.5, "duration": 91852.5, "weight": 74254.93}, {"library": "Efford Library", "distance": 396130.56, "duration": 90824.12, "weight": 73466.38}, {"library": "Estover Library", "distance": 411697.16, "duration": 93219.25, "weight": 72923.48}, {"library": "North Prospect Library", "distance": 415306.94, "duration": 94118.67, "weight": 73892.53}, {"library": "Peverell Library", "distance": 413767.72, "duration": 93799.16, "weight": 73654.6}, {"library": "Plympton Library", "distance": 389504.06, "duration": 89122.42, "weight": 72086.43}, {"library": "Plymstock Library", "distance": 393034.81, "duration": 89899.87, "weight": 72824.88}, {"library": "Southway Library", "distance": 409420.97, "duration": 92799.09, "weight": 72450.98}, {"library": "St Budeaux Library", "distance": 413952.47, "duration": 94325.16, "weight": 73783.9}, {"library": "West Park Library", "distance": 412802.13, "duration": 94024.37, "weight": 73515.14}]