[{"library": "Central Library", "distance": 354828.28, "duration": 254883.48, "weight": 231581.59}, {"library": "Crownhill Library", "distance": 353854.41, "duration": 254182.31, "weight": 230852.5}, {"library": "Devonport Library", "distance": 357030.84, "duration": 256469.31, "weight": 232877.31}, {"library": "Efford Library", "distance": 351823.31, "duration": 252719.95, "weight": 229633.34}, {"library": "Estover Library", "distance": 351811.16, "duration": 252711.22, "weight": 229718.3}, {"library": "North Prospect Library", "distance": 356254.56, "duration": 255910.41, "weight": 232254.5}, {"library": "Peverell Library", "distance": 354448.69, "duration": 254610.2, "weight": 231169.11}, {"library": "Plympton Library", "distance": 347455.5, "duration": 249575.14, "weight": 226750.41}, {"library": "Plymstock Library", "distance": 351023.91, "duration": 252144.36, "weight": 229498.14}, {"library": "Southway Library", "distance": 352061.06, "duration": 252891.17, "weight": 229084.3}, {"library": "St Budeaux Library", "distance": 358398.81, "duration": 257454.33, "weight": 233248.28}, {"library": "West Park Library", "distance": 356621.56, "duration": 256174.73, "weight": 231933.86}]