[{"library": "Central Library", "distance": 384615.34, "duration": 278283.63, "weight": 249238.69}, {"library": "Crownhill Library", "distance": 380656.19, "duration": 275433.22, "weight": 246810.78}, {"library": "Devonport Library", "distance": 386475.19, "duration": 279622.84, "weight": 250442.2}, {"library": "Efford Library", "distance": 381610.41, "duration": 276120.09, "weight": 247290.42}, {"library": "Estover Library", "distance": 380893, "duration": 275603.72, "weight": 246724.41}, {"library": "North Prospect Library", "distance": 384121.84, "duration": 277928.47, "weight": 248989.73}, {"library": "Peverell Library", "distance": 382666.75, "duration": 276880.81, "weight": 248116.25}, {"library": "Plympton Library", "distance": 377242.56, "duration": 272975.28, "weight": 244407.5}, {"library": "Plymstock Library", "distance": 381807.84, "duration": 276262.25, "weight": 247215.34}, {"library": "Southway Library", "distance": 378301.66, "duration": 273737.97, "weight": 244924.67}, {"library": "St Budeaux Library", "distance": 384639.41, "duration": 278301.13, "weight": 249088.67}, {"library": "West Park Library", "distance": 382862.06, "duration": 277021.44, "weight": 247774.17}]