[{"library": "Central Library", "distance": 1241058.63, "duration": 420423.91, "weight": 405254.53}, {"library": "Crownhill Library", "distance": 1245619, "duration": 423707.31, "weight": 408171.72}, {"library": "Devonport Library", "distance": 1241781.88, "duration": 420944.66, "weight": 405865.84}, {"library": "Efford Library", "distance": 1244446.75, "duration": 422863.34, "weight": 407405.69}, {"library": "Estover Library", "distance": 1247353, "duration": 424955.78, "weight": 409283.59}, {"library": "North Prospect Library", "distance": 1243317.88, "duration": 422050.5, "weight": 406849.44}, {"library": "Peverell Library", "distance": 1243673.88, "duration": 422306.81, "weight": 406855.88}, {"library": "Plympton Library", "distance": 1248560.13, "duration": 425824.88, "weight": 410333.81}, {"library": "Plymstock Library", "distance": 1245317.63, "duration": 423490.38, "weight": 408248.06}, {"library": "Southway Library", "distance": 1248904.25, "duration": 426072.63, "weight": 410441.13}, {"library": "St Budeaux Library", "distance": 1245334.63, "duration": 423502.56, "weight": 408052.91}, {"library": "West Park Library", "distance": 1246175.13, "duration": 424107.72, "weight": 408673.69}]