[{"library": "Central Library", "distance": 355637.34, "duration": 256550.78, "weight": 229600.22}, {"library": "Crownhill Library", "distance": 354663.47, "duration": 255849.63, "weight": 228871.13}, {"library": "Devonport Library", "distance": 357839.91, "duration": 258136.63, "weight": 230895.95}, {"library": "Efford Library", "distance": 352632.41, "duration": 254387.25, "weight": 227651.97}, {"library": "Estover Library", "distance": 352620.22, "duration": 254378.52, "weight": 227736.92}, {"library": "North Prospect Library", "distance": 357063.63, "duration": 257577.72, "weight": 230273.13}, {"library": "Peverell Library", "distance": 355257.75, "duration": 256277.52, "weight": 229187.73}, {"library": "Plympton Library", "distance": 348264.56, "duration": 251242.44, "weight": 224769.03}, {"library": "Plymstock Library", "distance": 351832.97, "duration": 253811.67, "weight": 227516.77}, {"library": "Southway Library", "distance": 352870.13, "duration": 254558.48, "weight": 227102.92}, {"library": "St Budeaux Library", "distance": 359207.88, "duration": 259121.63, "weight": 231266.91}, {"library": "West Park Library", "distance": 357430.63, "duration": 257842.03, "weight": 229952.48}]