[{"library": "Central Library", "distance": 351552.47, "duration": 254040.08, "weight": 229393.97}, {"library": "Crownhill Library", "distance": 350578.59, "duration": 253338.92, "weight": 228664.86}, {"library": "Devonport Library", "distance": 353755.03, "duration": 255625.91, "weight": 230689.69}, {"library": "Efford Library", "distance": 348547.5, "duration": 251876.55, "weight": 227445.7}, {"library": "Estover Library", "distance": 348535.34, "duration": 251867.81, "weight": 227530.66}, {"library": "North Prospect Library", "distance": 352978.72, "duration": 255067, "weight": 230066.86}, {"library": "Peverell Library", "distance": 351172.88, "duration": 253766.8, "weight": 228981.47}, {"library": "Plympton Library", "distance": 344179.69, "duration": 248731.73, "weight": 224562.77}, {"library": "Plymstock Library", "distance": 347748.09, "duration": 251300.95, "weight": 227310.5}, {"library": "Southway Library", "distance": 348785.25, "duration": 252047.78, "weight": 226896.66}, {"library": "St Budeaux Library", "distance": 355123, "duration": 256610.92, "weight": 231060.66}, {"library": "West Park Library", "distance": 353345.75, "duration": 255331.33, "weight": 229746.23}]