[{"library": "Central Library", "distance": 369948.91, "duration": 90841.04, "weight": 65480.24}, {"library": "Crownhill Library", "distance": 383591.44, "duration": 93020.9, "weight": 64891.73}, {"library": "Devonport Library", "distance": 372837.41, "duration": 91511.16, "weight": 66024.52}, {"library": "Efford Library", "distance": 367746.47, "duration": 90482.77, "weight": 65235.96}, {"library": "Estover Library", "distance": 383313.06, "duration": 92877.91, "weight": 64693.07}, {"library": "North Prospect Library", "distance": 386922.84, "duration": 93777.33, "weight": 65662.12}, {"library": "Peverell Library", "distance": 385383.63, "duration": 93457.81, "weight": 65424.19}, {"library": "Plympton Library", "distance": 361119.97, "duration": 88781.08, "weight": 63856.02}, {"library": "Plymstock Library", "distance": 364650.72, "duration": 89558.52, "weight": 64594.46}, {"library": "Southway Library", "distance": 381036.84, "duration": 92457.75, "weight": 64220.57}, {"library": "St Budeaux Library", "distance": 385568.38, "duration": 93983.82, "weight": 65553.48}, {"library": "West Park Library", "distance": 384418.03, "duration": 93683.02, "weight": 65284.72}]