[{"library": "Central Library", "distance": 409929.09, "duration": 15250.74, "weight": 15446.5}, {"library": "Crownhill Library", "distance": 407130.19, "duration": 15152.66, "weight": 15348.4}, {"library": "Devonport Library", "distance": 410987.78, "duration": 15352.32, "weight": 15548.07}, {"library": "Efford Library", "distance": 406073.81, "duration": 15290.46, "weight": 15486.2}, {"library": "Estover Library", "distance": 406431.19, "duration": 15083.95, "weight": 15279.69}, {"library": "North Prospect Library", "distance": 409278.66, "duration": 15204.45, "weight": 15400.19}, {"library": "Peverell Library", "distance": 407496.69, "duration": 15050.99, "weight": 15246.72}, {"library": "Plympton Library", "distance": 400486.09, "duration": 14910.58, "weight": 15106.32}, {"library": "Plymstock Library", "distance": 407788.78, "duration": 15269.84, "weight": 15465.59}, {"library": "Southway Library", "distance": 411124.44, "duration": 15297.77, "weight": 15493.52}, {"library": "St Budeaux Library", "distance": 410927.66, "duration": 15147.29, "weight": 15343.03}, {"library": "West Park Library", "distance": 411118.97, "duration": 15193.2, "weight": 15388.94}]