[{"library": "Central Library", "distance": 502239.06, "duration": 18396.5, "weight": 18475.71}, {"library": "Crownhill Library", "distance": 499440.13, "duration": 18298.42, "weight": 18377.61}, {"library": "Devonport Library", "distance": 503297.75, "duration": 18498.07, "weight": 18577.28}, {"library": "Efford Library", "distance": 498383.75, "duration": 18436.22, "weight": 18515.41}, {"library": "Estover Library", "distance": 498741.16, "duration": 18229.7, "weight": 18308.89}, {"library": "North Prospect Library", "distance": 501588.59, "duration": 18350.21, "weight": 18429.4}, {"library": "Peverell Library", "distance": 499806.66, "duration": 18196.75, "weight": 18275.93}, {"library": "Plympton Library", "distance": 492796.06, "duration": 18056.33, "weight": 18135.53}, {"library": "Plymstock Library", "distance": 500098.75, "duration": 18415.6, "weight": 18494.79}, {"library": "Southway Library", "distance": 503434.41, "duration": 18443.52, "weight": 18522.72}, {"library": "St Budeaux Library", "distance": 503237.63, "duration": 18293.05, "weight": 18372.24}, {"library": "West Park Library", "distance": 503428.94, "duration": 18338.95, "weight": 18418.15}]