[{"library": "Central Library", "distance": 359731.34, "duration": 261393.33, "weight": 233748.13}, {"library": "Crownhill Library", "distance": 358757.47, "duration": 260692.17, "weight": 233019.02}, {"library": "Devonport Library", "distance": 361933.91, "duration": 262979.16, "weight": 235043.84}, {"library": "Efford Library", "distance": 356726.38, "duration": 259229.8, "weight": 231799.86}, {"library": "Estover Library", "distance": 356714.22, "duration": 259221.06, "weight": 231884.81}, {"library": "North Prospect Library", "distance": 361157.63, "duration": 262420.25, "weight": 234421.03}, {"library": "Peverell Library", "distance": 359351.75, "duration": 261120.06, "weight": 233335.63}, {"library": "Plympton Library", "distance": 352358.56, "duration": 256084.98, "weight": 228916.92}, {"library": "Plymstock Library", "distance": 355926.97, "duration": 258654.22, "weight": 231664.66}, {"library": "Southway Library", "distance": 356964.13, "duration": 259401.03, "weight": 231250.81}, {"library": "St Budeaux Library", "distance": 363301.88, "duration": 263964.19, "weight": 235414.81}, {"library": "West Park Library", "distance": 361524.63, "duration": 262684.59, "weight": 234100.39}]