[{"library": "Central Library", "distance": 516546.53, "duration": 18950.21, "weight": 18992.37}, {"library": "Crownhill Library", "distance": 513747.59, "duration": 18852.13, "weight": 18894.27}, {"library": "Devonport Library", "distance": 517605.22, "duration": 19051.78, "weight": 19093.94}, {"library": "Efford Library", "distance": 512691.22, "duration": 18989.93, "weight": 19032.07}, {"library": "Estover Library", "distance": 513048.63, "duration": 18783.42, "weight": 18825.56}, {"library": "North Prospect Library", "distance": 515896.06, "duration": 18903.92, "weight": 18946.07}, {"library": "Peverell Library", "distance": 514114.09, "duration": 18750.46, "weight": 18792.6}, {"library": "Plympton Library", "distance": 507103.53, "duration": 18610.05, "weight": 18652.19}, {"library": "Plymstock Library", "distance": 514406.22, "duration": 18969.31, "weight": 19011.46}, {"library": "Southway Library", "distance": 517741.88, "duration": 18997.24, "weight": 19039.39}, {"library": "St Budeaux Library", "distance": 517545.09, "duration": 18846.76, "weight": 18888.9}, {"library": "West Park Library", "distance": 517736.41, "duration": 18892.67, "weight": 18934.81}]