[{"library": "Central Library", "distance": 471778.25, "duration": 338006.31, "weight": 305348.97}, {"library": "Crownhill Library", "distance": 468037.06, "duration": 335312.81, "weight": 303432.91}, {"library": "Devonport Library", "distance": 473980.84, "duration": 339592.13, "weight": 306644.72}, {"library": "Efford Library", "distance": 468773.31, "duration": 335842.78, "weight": 303400.72}, {"library": "Estover Library", "distance": 468273.84, "duration": 335483.31, "weight": 303346.5}, {"library": "North Prospect Library", "distance": 471502.72, "duration": 337808.09, "weight": 305611.84}, {"library": "Peverell Library", "distance": 470047.63, "duration": 336760.44, "weight": 304738.38}, {"library": "Plympton Library", "distance": 464405.47, "duration": 332697.97, "weight": 300517.78}, {"library": "Plymstock Library", "distance": 467973.88, "duration": 335267.19, "weight": 303265.53}, {"library": "Southway Library", "distance": 465682.53, "duration": 333617.56, "weight": 301546.78}, {"library": "St Budeaux Library", "distance": 472020.28, "duration": 338180.72, "weight": 305710.78}, {"library": "West Park Library", "distance": 470243.03, "duration": 336901.13, "weight": 304396.38}]