[{"library": "Central Library", "distance": 563631.56, "duration": 131286.38, "weight": 100725.55}, {"library": "Crownhill Library", "distance": 577274.06, "duration": 133466.23, "weight": 100137.04}, {"library": "Devonport Library", "distance": 566520.06, "duration": 131956.48, "weight": 101269.82}, {"library": "Efford Library", "distance": 561429.13, "duration": 130928.1, "weight": 100481.27}, {"library": "Estover Library", "distance": 576995.69, "duration": 133323.23, "weight": 99938.38}, {"library": "North Prospect Library", "distance": 580605.5, "duration": 134222.66, "weight": 100907.43}, {"library": "Peverell Library", "distance": 579066.25, "duration": 133903.14, "weight": 100669.5}, {"library": "Plympton Library", "distance": 554802.63, "duration": 129226.41, "weight": 99101.32}, {"library": "Plymstock Library", "distance": 558333.38, "duration": 130003.86, "weight": 99839.77}, {"library": "Southway Library", "distance": 574719.5, "duration": 132903.08, "weight": 99465.88}, {"library": "St Budeaux Library", "distance": 579251, "duration": 134429.16, "weight": 100798.8}, {"library": "West Park Library", "distance": 578100.63, "duration": 134128.36, "weight": 100530.03}]