[{"library": "Central Library", "distance": 356296.41, "duration": 257820.38, "weight": 232666.44}, {"library": "Crownhill Library", "distance": 355322.53, "duration": 257119.2, "weight": 231937.33}, {"library": "Devonport Library", "distance": 358498.97, "duration": 259406.2, "weight": 233962.16}, {"library": "Efford Library", "distance": 353291.47, "duration": 255656.84, "weight": 230718.17}, {"library": "Estover Library", "distance": 353279.28, "duration": 255648.09, "weight": 230803.13}, {"library": "North Prospect Library", "distance": 357722.69, "duration": 258847.3, "weight": 233339.34}, {"library": "Peverell Library", "distance": 355916.81, "duration": 257547.09, "weight": 232253.94}, {"library": "Plympton Library", "distance": 348923.63, "duration": 252512.02, "weight": 227835.25}, {"library": "Plymstock Library", "distance": 352492.03, "duration": 255081.25, "weight": 230582.97}, {"library": "Southway Library", "distance": 353529.19, "duration": 255828.06, "weight": 230169.13}, {"library": "St Budeaux Library", "distance": 359866.94, "duration": 260391.22, "weight": 234333.13}, {"library": "West Park Library", "distance": 358089.69, "duration": 259111.63, "weight": 233018.7}]