[{"library": "Central Library", "distance": 391541.09, "duration": 89176.68, "weight": 69160.57}, {"library": "Crownhill Library", "distance": 405183.63, "duration": 91356.54, "weight": 68572.06}, {"library": "Devonport Library", "distance": 394429.59, "duration": 89846.79, "weight": 69704.84}, {"library": "Efford Library", "distance": 389338.66, "duration": 88818.41, "weight": 68916.29}, {"library": "Estover Library", "distance": 404905.25, "duration": 91213.55, "weight": 68373.4}, {"library": "North Prospect Library", "distance": 408515.03, "duration": 92112.97, "weight": 69342.45}, {"library": "Peverell Library", "distance": 406975.81, "duration": 91793.45, "weight": 69104.52}, {"library": "Plympton Library", "distance": 382712.16, "duration": 87116.72, "weight": 67536.34}, {"library": "Plymstock Library", "distance": 386242.91, "duration": 87894.16, "weight": 68274.8}, {"library": "Southway Library", "distance": 402629.03, "duration": 90793.39, "weight": 67900.91}, {"library": "St Budeaux Library", "distance": 407160.56, "duration": 92319.46, "weight": 69233.82}, {"library": "West Park Library", "distance": 406010.19, "duration": 92018.66, "weight": 68965.05}]