[{"library": "Central Library", "distance": 351782.88, "duration": 14791.64, "weight": 14763.31}, {"library": "Crownhill Library", "distance": 348983.94, "duration": 14693.57, "weight": 14665.21}, {"library": "Devonport Library", "distance": 352841.56, "duration": 14893.22, "weight": 14864.88}, {"library": "Efford Library", "distance": 347927.56, "duration": 14831.37, "weight": 14803.01}, {"library": "Estover Library", "distance": 348284.97, "duration": 14624.85, "weight": 14596.5}, {"library": "North Prospect Library", "distance": 351132.44, "duration": 14745.35, "weight": 14717}, {"library": "Peverell Library", "distance": 349350.47, "duration": 14591.89, "weight": 14563.53}, {"library": "Plympton Library", "distance": 342339.88, "duration": 14451.48, "weight": 14423.13}, {"library": "Plymstock Library", "distance": 349642.56, "duration": 14810.75, "weight": 14782.4}, {"library": "Southway Library", "distance": 352978.22, "duration": 14838.67, "weight": 14810.33}, {"library": "St Budeaux Library", "distance": 352781.44, "duration": 14688.19, "weight": 14659.84}, {"library": "West Park Library", "distance": 352972.75, "duration": 14734.1, "weight": 14705.75}]