[{"library": "Central Library", "distance": 619796.25, "duration": 22627.54, "weight": 22938.85}, {"library": "Crownhill Library", "distance": 616997.38, "duration": 22529.46, "weight": 22840.76}, {"library": "Devonport Library", "distance": 620855, "duration": 22729.11, "weight": 23040.43}, {"library": "Efford Library", "distance": 615941, "duration": 22667.26, "weight": 22978.56}, {"library": "Estover Library", "distance": 616298.38, "duration": 22460.75, "weight": 22772.04}, {"library": "North Prospect Library", "distance": 619145.81, "duration": 22581.25, "weight": 22892.55}, {"library": "Peverell Library", "distance": 617363.88, "duration": 22427.79, "weight": 22739.08}, {"library": "Plympton Library", "distance": 610353.25, "duration": 22287.38, "weight": 22598.67}, {"library": "Plymstock Library", "distance": 617655.94, "duration": 22646.64, "weight": 22957.94}, {"library": "Southway Library", "distance": 620991.63, "duration": 22674.57, "weight": 22985.87}, {"library": "St Budeaux Library", "distance": 620794.81, "duration": 22524.09, "weight": 22835.38}, {"library": "West Park Library", "distance": 620986.13, "duration": 22570, "weight": 22881.29}]