[{"library": "Central Library", "distance": 269246.44, "duration": 64552.79, "weight": 51921.52}, {"library": "Crownhill Library", "distance": 282888.97, "duration": 66732.66, "weight": 51333.01}, {"library": "Devonport Library", "distance": 272134.97, "duration": 65222.91, "weight": 52465.79}, {"library": "Efford Library", "distance": 267044, "duration": 64194.52, "weight": 51677.23}, {"library": "Estover Library", "distance": 282610.63, "duration": 66589.66, "weight": 51134.34}, {"library": "North Prospect Library", "distance": 286220.38, "duration": 67489.09, "weight": 52103.39}, {"library": "Peverell Library", "distance": 284681.16, "duration": 67169.56, "weight": 51865.47}, {"library": "Plympton Library", "distance": 260417.5, "duration": 62492.83, "weight": 50297.29}, {"library": "Plymstock Library", "distance": 263948.28, "duration": 63270.28, "weight": 51035.74}, {"library": "Southway Library", "distance": 280334.41, "duration": 66169.51, "weight": 50661.85}, {"library": "St Budeaux Library", "distance": 284865.94, "duration": 67695.58, "weight": 51994.76}, {"library": "West Park Library", "distance": 283715.56, "duration": 67394.77, "weight": 51726}]