[{"library": "Central Library", "distance": 392101.41, "duration": 14826.91, "weight": 14804.51}, {"library": "Crownhill Library", "distance": 389302.5, "duration": 14728.83, "weight": 14706.41}, {"library": "Devonport Library", "distance": 393160.13, "duration": 14928.49, "weight": 14906.08}, {"library": "Efford Library", "distance": 388246.13, "duration": 14866.64, "weight": 14844.21}, {"library": "Estover Library", "distance": 388603.5, "duration": 14660.12, "weight": 14637.69}, {"library": "North Prospect Library", "distance": 391450.97, "duration": 14780.62, "weight": 14758.2}, {"library": "Peverell Library", "distance": 389669, "duration": 14627.16, "weight": 14604.73}, {"library": "Plympton Library", "distance": 382658.41, "duration": 14486.75, "weight": 14464.33}, {"library": "Plymstock Library", "distance": 389961.09, "duration": 14846.01, "weight": 14823.6}, {"library": "Southway Library", "distance": 393296.75, "duration": 14873.94, "weight": 14851.53}, {"library": "St Budeaux Library", "distance": 393099.97, "duration": 14723.46, "weight": 14701.04}, {"library": "West Park Library", "distance": 393291.28, "duration": 14769.37, "weight": 14746.95}]