[{"library": "Central Library", "distance": 333182.63, "duration": 13434.93, "weight": 13415.73}, {"library": "Crownhill Library", "distance": 330383.69, "duration": 13336.85, "weight": 13317.63}, {"library": "Devonport Library", "distance": 334241.31, "duration": 13536.5, "weight": 13517.3}, {"library": "Efford Library", "distance": 329327.31, "duration": 13474.65, "weight": 13455.43}, {"library": "Estover Library", "distance": 329684.72, "duration": 13268.14, "weight": 13248.92}, {"library": "North Prospect Library", "distance": 332532.16, "duration": 13388.64, "weight": 13369.42}, {"library": "Peverell Library", "distance": 330750.19, "duration": 13235.18, "weight": 13215.95}, {"library": "Plympton Library", "distance": 323739.63, "duration": 13094.77, "weight": 13075.55}, {"library": "Plymstock Library", "distance": 331042.28, "duration": 13454.03, "weight": 13434.82}, {"library": "Southway Library", "distance": 334377.97, "duration": 13481.96, "weight": 13462.75}, {"library": "St Budeaux Library", "distance": 334181.16, "duration": 13331.48, "weight": 13312.26}, {"library": "West Park Library", "distance": 334372.47, "duration": 13377.39, "weight": 13358.17}]