[{"library": "Central Library", "distance": 460941.66, "duration": 332722.34, "weight": 299613.81}, {"library": "Crownhill Library", "distance": 457200.47, "duration": 330028.84, "weight": 297697.72}, {"library": "Devonport Library", "distance": 463144.22, "duration": 334308.16, "weight": 300909.53}, {"library": "Efford Library", "distance": 457936.69, "duration": 330558.81, "weight": 297665.56}, {"library": "Estover Library", "distance": 457437.25, "duration": 330199.34, "weight": 297611.34}, {"library": "North Prospect Library", "distance": 460666.13, "duration": 332524.13, "weight": 299876.69}, {"library": "Peverell Library", "distance": 459211.03, "duration": 331476.44, "weight": 299003.19}, {"library": "Plympton Library", "distance": 453568.88, "duration": 327413.97, "weight": 294782.63}, {"library": "Plymstock Library", "distance": 457137.28, "duration": 329983.22, "weight": 297530.34}, {"library": "Southway Library", "distance": 454845.91, "duration": 328333.59, "weight": 295811.63}, {"library": "St Budeaux Library", "distance": 461183.66, "duration": 332896.75, "weight": 299975.63}, {"library": "West Park Library", "distance": 459406.44, "duration": 331617.16, "weight": 298661.19}]