[{"library": "Central Library", "distance": 591429.81, "duration": 135075.83, "weight": 107072.46}, {"library": "Crownhill Library", "distance": 605072.38, "duration": 137255.69, "weight": 106483.96}, {"library": "Devonport Library", "distance": 594318.31, "duration": 135745.94, "weight": 107616.74}, {"library": "Efford Library", "distance": 589227.38, "duration": 134717.56, "weight": 106828.19}, {"library": "Estover Library", "distance": 604794, "duration": 137112.7, "weight": 106285.3}, {"library": "North Prospect Library", "distance": 608403.75, "duration": 138012.13, "weight": 107254.34}, {"library": "Peverell Library", "distance": 606864.56, "duration": 137692.59, "weight": 107016.41}, {"library": "Plympton Library", "distance": 582600.88, "duration": 133015.88, "weight": 105448.24}, {"library": "Plymstock Library", "distance": 586131.69, "duration": 133793.31, "weight": 106186.69}, {"library": "Southway Library", "distance": 602517.81, "duration": 136692.55, "weight": 105812.8}, {"library": "St Budeaux Library", "distance": 607049.31, "duration": 138218.61, "weight": 107145.71}, {"library": "West Park Library", "distance": 605898.94, "duration": 137917.81, "weight": 106876.95}]