[{"library": "Central Library", "distance": 354922.81, "duration": 255245.89, "weight": 231763.05}, {"library": "Crownhill Library", "distance": 353948.91, "duration": 254544.73, "weight": 231033.95}, {"library": "Devonport Library", "distance": 357125.38, "duration": 256831.73, "weight": 233058.77}, {"library": "Efford Library", "distance": 351917.84, "duration": 253082.36, "weight": 229814.8}, {"library": "Estover Library", "distance": 351905.69, "duration": 253073.63, "weight": 229899.73}, {"library": "North Prospect Library", "distance": 356349.06, "duration": 256272.83, "weight": 232435.95}, {"library": "Peverell Library", "distance": 354543.22, "duration": 254972.63, "weight": 231350.56}, {"library": "Plympton Library", "distance": 347550, "duration": 249937.55, "weight": 226931.86}, {"library": "Plymstock Library", "distance": 351118.41, "duration": 252506.78, "weight": 229679.58}, {"library": "Southway Library", "distance": 352155.56, "duration": 253253.59, "weight": 229265.73}, {"library": "St Budeaux Library", "distance": 358493.31, "duration": 257816.73, "weight": 233429.73}, {"library": "West Park Library", "distance": 356716.09, "duration": 256537.14, "weight": 232115.31}]