[{"library": "Central Library", "distance": 464487.75, "duration": 17330.58, "weight": 17234.47}, {"library": "Crownhill Library", "distance": 461688.84, "duration": 17232.5, "weight": 17136.37}, {"library": "Devonport Library", "distance": 465546.47, "duration": 17432.16, "weight": 17336.04}, {"library": "Efford Library", "distance": 460632.47, "duration": 17370.31, "weight": 17274.17}, {"library": "Estover Library", "distance": 460989.84, "duration": 17163.79, "weight": 17067.66}, {"library": "North Prospect Library", "distance": 463837.31, "duration": 17284.29, "weight": 17188.16}, {"library": "Peverell Library", "distance": 462055.34, "duration": 17130.83, "weight": 17034.7}, {"library": "Plympton Library", "distance": 455044.75, "duration": 16990.42, "weight": 16894.29}, {"library": "Plymstock Library", "distance": 462347.44, "duration": 17349.69, "weight": 17253.56}, {"library": "Southway Library", "distance": 465683.09, "duration": 17377.61, "weight": 17281.49}, {"library": "St Budeaux Library", "distance": 465486.31, "duration": 17227.13, "weight": 17131}, {"library": "West Park Library", "distance": 465677.63, "duration": 17273.04, "weight": 17176.91}]