[{"library": "Central Library", "distance": 465654.5, "duration": 17685.17, "weight": 17685.58}, {"library": "Crownhill Library", "distance": 462855.56, "duration": 17587.09, "weight": 17587.48}, {"library": "Devonport Library", "distance": 466713.19, "duration": 17786.74, "weight": 17787.15}, {"library": "Efford Library", "distance": 461799.19, "duration": 17724.89, "weight": 17725.29}, {"library": "Estover Library", "distance": 462156.59, "duration": 17518.37, "weight": 17518.77}, {"library": "North Prospect Library", "distance": 465004.03, "duration": 17638.88, "weight": 17639.28}, {"library": "Peverell Library", "distance": 463222.06, "duration": 17485.42, "weight": 17485.8}, {"library": "Plympton Library", "distance": 456211.5, "duration": 17345, "weight": 17345.4}, {"library": "Plymstock Library", "distance": 463514.16, "duration": 17704.27, "weight": 17704.67}, {"library": "Southway Library", "distance": 466849.84, "duration": 17732.19, "weight": 17732.6}, {"library": "St Budeaux Library", "distance": 466653.03, "duration": 17581.72, "weight": 17582.11}, {"library": "West Park Library", "distance": 466844.34, "duration": 17627.62, "weight": 17628.02}]