[{"library": "Central Library", "distance": 482012.81, "duration": 107414.47, "weight": 89344.07}, {"library": "Crownhill Library", "distance": 495655.34, "duration": 109594.33, "weight": 88755.56}, {"library": "Devonport Library", "distance": 484901.31, "duration": 108084.58, "weight": 89888.34}, {"library": "Efford Library", "distance": 479810.38, "duration": 107056.2, "weight": 89099.79}, {"library": "Estover Library", "distance": 495376.97, "duration": 109451.34, "weight": 88556.9}, {"library": "North Prospect Library", "distance": 498986.75, "duration": 110350.76, "weight": 89525.95}, {"library": "Peverell Library", "distance": 497447.53, "duration": 110031.23, "weight": 89288.02}, {"library": "Plympton Library", "distance": 473183.88, "duration": 105354.51, "weight": 87719.84}, {"library": "Plymstock Library", "distance": 476714.63, "duration": 106131.95, "weight": 88458.29}, {"library": "Southway Library", "distance": 493100.75, "duration": 109031.18, "weight": 88084.41}, {"library": "St Budeaux Library", "distance": 497632.28, "duration": 110557.25, "weight": 89417.31}, {"library": "West Park Library", "distance": 496481.94, "duration": 110256.45, "weight": 89148.55}]