[{"library": "Central Library", "distance": 507746.59, "duration": 13481.91, "weight": 18821.28}, {"library": "Crownhill Library", "distance": 504947.66, "duration": 13383.83, "weight": 18723.18}, {"library": "Devonport Library", "distance": 508805.28, "duration": 13583.49, "weight": 18922.85}, {"library": "Efford Library", "distance": 503891.28, "duration": 13521.63, "weight": 18860.98}, {"library": "Estover Library", "distance": 504248.69, "duration": 13315.12, "weight": 18654.47}, {"library": "North Prospect Library", "distance": 507096.13, "duration": 13435.62, "weight": 18774.97}, {"library": "Peverell Library", "distance": 505314.16, "duration": 13282.16, "weight": 18621.51}, {"library": "Plympton Library", "distance": 498303.59, "duration": 13141.75, "weight": 18481.1}, {"library": "Plymstock Library", "distance": 505606.28, "duration": 13501.01, "weight": 18840.37}, {"library": "Southway Library", "distance": 508941.94, "duration": 13528.94, "weight": 18868.3}, {"library": "St Budeaux Library", "distance": 508745.16, "duration": 13378.46, "weight": 18717.81}, {"library": "West Park Library", "distance": 508936.47, "duration": 13424.37, "weight": 18763.72}]