[{"library": "Central Library", "distance": 340392.34, "duration": 80958.88, "weight": 63863.71}, {"library": "Crownhill Library", "distance": 354034.84, "duration": 83138.75, "weight": 63275.2}, {"library": "Devonport Library", "distance": 343280.84, "duration": 81629, "weight": 64407.98}, {"library": "Efford Library", "distance": 338189.91, "duration": 80600.62, "weight": 63619.43}, {"library": "Estover Library", "distance": 353756.5, "duration": 82995.75, "weight": 63076.54}, {"library": "North Prospect Library", "distance": 357366.28, "duration": 83895.18, "weight": 64045.59}, {"library": "Peverell Library", "distance": 355827.03, "duration": 83575.66, "weight": 63807.66}, {"library": "Plympton Library", "distance": 331563.38, "duration": 78898.92, "weight": 62239.48}, {"library": "Plymstock Library", "distance": 335094.16, "duration": 79676.37, "weight": 62977.93}, {"library": "Southway Library", "distance": 351480.28, "duration": 82575.6, "weight": 62604.04}, {"library": "St Budeaux Library", "distance": 356011.81, "duration": 84101.66, "weight": 63936.96}, {"library": "West Park Library", "distance": 354861.44, "duration": 83800.87, "weight": 63668.2}]