[{"library": "Central Library", "distance": 410448.41, "duration": 297846.41, "weight": 268522}, {"library": "Crownhill Library", "distance": 409474.53, "duration": 297145.25, "weight": 267792.91}, {"library": "Devonport Library", "distance": 412650.97, "duration": 299432.25, "weight": 269817.72}, {"library": "Efford Library", "distance": 407443.44, "duration": 295682.88, "weight": 266573.75}, {"library": "Estover Library", "distance": 407431.28, "duration": 295674.16, "weight": 266658.69}, {"library": "North Prospect Library", "distance": 411874.69, "duration": 298873.34, "weight": 269194.91}, {"library": "Peverell Library", "distance": 410068.81, "duration": 297573.13, "weight": 268109.5}, {"library": "Plympton Library", "distance": 403075.63, "duration": 292538.06, "weight": 263690.81}, {"library": "Plymstock Library", "distance": 407640.91, "duration": 295825.06, "weight": 266498.66}, {"library": "Southway Library", "distance": 407694, "duration": 295863.34, "weight": 266032.78}, {"library": "St Budeaux Library", "distance": 414031.75, "duration": 300426.5, "weight": 270196.78}, {"library": "West Park Library", "distance": 412254.41, "duration": 299146.81, "weight": 268882.28}]