[{"library": "Central Library", "distance": 246549.25, "duration": 10960.08, "weight": 10826.11}, {"library": "Crownhill Library", "distance": 243750.31, "duration": 10862, "weight": 10728.01}, {"library": "Devonport Library", "distance": 247607.94, "duration": 11061.66, "weight": 10927.68}, {"library": "Efford Library", "distance": 242693.95, "duration": 10999.81, "weight": 10865.81}, {"library": "Estover Library", "distance": 243051.34, "duration": 10793.29, "weight": 10659.3}, {"library": "North Prospect Library", "distance": 245898.8, "duration": 10913.79, "weight": 10779.8}, {"library": "Peverell Library", "distance": 244116.83, "duration": 10760.33, "weight": 10626.33}, {"library": "Plympton Library", "distance": 237106.25, "duration": 10619.92, "weight": 10485.93}, {"library": "Plymstock Library", "distance": 244408.92, "duration": 10979.18, "weight": 10845.2}, {"library": "Southway Library", "distance": 247744.59, "duration": 11007.11, "weight": 10873.13}, {"library": "St Budeaux Library", "distance": 247547.8, "duration": 10856.63, "weight": 10722.64}, {"library": "West Park Library", "distance": 247739.11, "duration": 10902.54, "weight": 10768.55}]