[{"library": "Central Library", "distance": 505069.69, "duration": 15145.39, "weight": 18690.6}, {"library": "Crownhill Library", "distance": 502270.78, "duration": 15047.31, "weight": 18592.5}, {"library": "Devonport Library", "distance": 506128.41, "duration": 15246.96, "weight": 18792.17}, {"library": "Efford Library", "distance": 501214.41, "duration": 15185.11, "weight": 18730.3}, {"library": "Estover Library", "distance": 501571.81, "duration": 14978.6, "weight": 18523.78}, {"library": "North Prospect Library", "distance": 504419.25, "duration": 15099.1, "weight": 18644.29}, {"library": "Peverell Library", "distance": 502637.28, "duration": 14945.64, "weight": 18490.82}, {"library": "Plympton Library", "distance": 495626.69, "duration": 14805.23, "weight": 18350.41}, {"library": "Plymstock Library", "distance": 502929.38, "duration": 15164.49, "weight": 18709.69}, {"library": "Southway Library", "distance": 506265.03, "duration": 15192.42, "weight": 18737.62}, {"library": "St Budeaux Library", "distance": 506068.25, "duration": 15041.94, "weight": 18587.13}, {"library": "West Park Library", "distance": 506259.56, "duration": 15087.85, "weight": 18633.04}]