[{"library": "Central Library", "distance": 358449.16, "duration": 254413.5, "weight": 232581.73}, {"library": "Crownhill Library", "distance": 357475.28, "duration": 253712.34, "weight": 231852.64}, {"library": "Devonport Library", "distance": 360651.75, "duration": 255999.33, "weight": 233877.45}, {"library": "Efford Library", "distance": 355444.22, "duration": 252249.97, "weight": 230633.48}, {"library": "Estover Library", "distance": 355432.06, "duration": 252241.23, "weight": 230718.42}, {"library": "North Prospect Library", "distance": 359875.44, "duration": 255440.42, "weight": 233254.64}, {"library": "Peverell Library", "distance": 358069.59, "duration": 254140.22, "weight": 232169.25}, {"library": "Plympton Library", "distance": 351076.38, "duration": 249105.16, "weight": 227750.55}, {"library": "Plymstock Library", "distance": 355641.66, "duration": 252392.14, "weight": 230558.41}, {"library": "Southway Library", "distance": 355694.75, "duration": 252430.42, "weight": 230092.53}, {"library": "St Budeaux Library", "distance": 362032.5, "duration": 256993.58, "weight": 234256.53}, {"library": "West Park Library", "distance": 360255.16, "duration": 255713.89, "weight": 232942.03}]