[{"library": "Central Library", "distance": 325740.97, "duration": 12795.92, "weight": 12548.58}, {"library": "Crownhill Library", "distance": 322942.03, "duration": 12697.84, "weight": 12450.49}, {"library": "Devonport Library", "distance": 326799.66, "duration": 12897.5, "weight": 12650.16}, {"library": "Efford Library", "distance": 321885.66, "duration": 12835.64, "weight": 12588.29}, {"library": "Estover Library", "distance": 322243.06, "duration": 12629.13, "weight": 12381.77}, {"library": "North Prospect Library", "distance": 325090.53, "duration": 12749.63, "weight": 12502.28}, {"library": "Peverell Library", "distance": 323308.56, "duration": 12596.17, "weight": 12348.81}, {"library": "Plympton Library", "distance": 316297.97, "duration": 12455.76, "weight": 12208.4}, {"library": "Plymstock Library", "distance": 323600.66, "duration": 12815.02, "weight": 12567.67}, {"library": "Southway Library", "distance": 326936.31, "duration": 12842.95, "weight": 12595.6}, {"library": "St Budeaux Library", "distance": 326739.53, "duration": 12692.47, "weight": 12445.12}, {"library": "West Park Library", "distance": 326930.84, "duration": 12738.38, "weight": 12491.02}]