[{"library": "Central Library", "distance": 556254.38, "duration": 126303.54, "weight": 98683.1}, {"library": "Crownhill Library", "distance": 569896.94, "duration": 128483.4, "weight": 98094.59}, {"library": "Devonport Library", "distance": 559142.88, "duration": 126973.65, "weight": 99227.38}, {"library": "Efford Library", "distance": 554051.94, "duration": 125945.27, "weight": 98438.82}, {"library": "Estover Library", "distance": 569618.56, "duration": 128340.41, "weight": 97895.93}, {"library": "North Prospect Library", "distance": 573228.31, "duration": 129239.83, "weight": 98864.98}, {"library": "Peverell Library", "distance": 571689.06, "duration": 128920.3, "weight": 98627.05}, {"library": "Plympton Library", "distance": 547425.44, "duration": 124243.58, "weight": 97058.88}, {"library": "Plymstock Library", "distance": 550956.19, "duration": 125021.02, "weight": 97797.33}, {"library": "Southway Library", "distance": 567342.31, "duration": 127920.25, "weight": 97423.44}, {"library": "St Budeaux Library", "distance": 571873.88, "duration": 129446.32, "weight": 98756.35}, {"library": "West Park Library", "distance": 570723.5, "duration": 129145.52, "weight": 98487.59}]