[{"library": "Central Library", "distance": 322682.5, "duration": 226989.36, "weight": 206201.06}, {"library": "Crownhill Library", "distance": 321708.59, "duration": 226288.19, "weight": 205471.97}, {"library": "Devonport Library", "distance": 324885.06, "duration": 228575.19, "weight": 207496.78}, {"library": "Efford Library", "distance": 319677.53, "duration": 224825.83, "weight": 204252.8}, {"library": "Estover Library", "distance": 319665.38, "duration": 224817.08, "weight": 204337.75}, {"library": "North Prospect Library", "distance": 324108.75, "duration": 228016.28, "weight": 206873.97}, {"library": "Peverell Library", "distance": 322302.91, "duration": 226716.08, "weight": 205788.58}, {"library": "Plympton Library", "distance": 315309.69, "duration": 221681, "weight": 201369.88}, {"library": "Plymstock Library", "distance": 319874.97, "duration": 224967.98, "weight": 204177.73}, {"library": "Southway Library", "distance": 321212.75, "duration": 225931.22, "weight": 204804.03}, {"library": "St Budeaux Library", "distance": 326033.66, "duration": 229402.19, "weight": 208134.8}, {"library": "West Park Library", "distance": 324697, "duration": 228439.8, "weight": 207303.17}]