[{"library": "Central Library", "distance": 344213.44, "duration": 248934.98, "weight": 223205.3}, {"library": "Crownhill Library", "distance": 343239.56, "duration": 248233.81, "weight": 222476.2}, {"library": "Devonport Library", "distance": 346416, "duration": 250520.81, "weight": 224501.03}, {"library": "Efford Library", "distance": 341208.5, "duration": 246771.45, "weight": 221257.05}, {"library": "Estover Library", "distance": 341196.31, "duration": 246762.7, "weight": 221342}, {"library": "North Prospect Library", "distance": 345639.72, "duration": 249961.91, "weight": 223878.2}, {"library": "Peverell Library", "distance": 343833.84, "duration": 248661.7, "weight": 222792.81}, {"library": "Plympton Library", "distance": 336840.66, "duration": 243626.63, "weight": 218374.11}, {"library": "Plymstock Library", "distance": 341405.94, "duration": 246913.61, "weight": 221181.97}, {"library": "Southway Library", "distance": 341459.03, "duration": 246951.91, "weight": 220716.09}, {"library": "St Budeaux Library", "distance": 347796.78, "duration": 251515.05, "weight": 224880.09}, {"library": "West Park Library", "distance": 346019.44, "duration": 250235.38, "weight": 223565.59}]