[{"library": "Central Library", "distance": 569100.75, "duration": 132234.91, "weight": 102897.81}, {"library": "Crownhill Library", "distance": 582743.25, "duration": 134414.77, "weight": 102309.3}, {"library": "Devonport Library", "distance": 571989.25, "duration": 132905.02, "weight": 103442.09}, {"library": "Efford Library", "distance": 566898.31, "duration": 131876.64, "weight": 102653.53}, {"library": "Estover Library", "distance": 582464.94, "duration": 134271.78, "weight": 102110.64}, {"library": "North Prospect Library", "distance": 586074.69, "duration": 135171.2, "weight": 103079.7}, {"library": "Peverell Library", "distance": 584535.44, "duration": 134851.67, "weight": 102841.77}, {"library": "Plympton Library", "distance": 560271.81, "duration": 130174.95, "weight": 101273.59}, {"library": "Plymstock Library", "distance": 563802.56, "duration": 130952.39, "weight": 102012.04}, {"library": "Southway Library", "distance": 580188.69, "duration": 133851.63, "weight": 101638.15}, {"library": "St Budeaux Library", "distance": 584720.25, "duration": 135377.69, "weight": 102971.06}, {"library": "West Park Library", "distance": 583569.88, "duration": 135076.89, "weight": 102702.3}]