[{"library": "Central Library", "distance": 418616.59, "duration": 300767.78, "weight": 271248.63}, {"library": "Crownhill Library", "distance": 414657.41, "duration": 297917.38, "weight": 268820.75}, {"library": "Devonport Library", "distance": 420476.41, "duration": 302107, "weight": 272452.16}, {"library": "Efford Library", "distance": 415611.63, "duration": 298604.25, "weight": 269300.38}, {"library": "Estover Library", "distance": 414894.22, "duration": 298087.88, "weight": 268734.34}, {"library": "North Prospect Library", "distance": 418123.09, "duration": 300412.63, "weight": 270999.69}, {"library": "Peverell Library", "distance": 416668, "duration": 299364.97, "weight": 270126.19}, {"library": "Plympton Library", "distance": 411243.78, "duration": 295459.44, "weight": 266417.44}, {"library": "Plymstock Library", "distance": 415809.06, "duration": 298746.41, "weight": 269225.31}, {"library": "Southway Library", "distance": 412302.91, "duration": 296222.13, "weight": 266934.63}, {"library": "St Budeaux Library", "distance": 418640.63, "duration": 300785.28, "weight": 271098.63}, {"library": "West Park Library", "distance": 416863.28, "duration": 299505.59, "weight": 269784.13}]