[{"library": "Central Library", "distance": 422059.41, "duration": 338900.03, "weight": 274306.19}, {"library": "Crownhill Library", "distance": 421085.5, "duration": 338198.88, "weight": 273577.09}, {"library": "Devonport Library", "distance": 424261.97, "duration": 340485.88, "weight": 275601.91}, {"library": "Efford Library", "distance": 419054.44, "duration": 336736.5, "weight": 272357.94}, {"library": "Estover Library", "distance": 419042.28, "duration": 336727.78, "weight": 272442.88}, {"library": "North Prospect Library", "distance": 423485.66, "duration": 339926.97, "weight": 274979.09}, {"library": "Peverell Library", "distance": 421679.81, "duration": 338626.78, "weight": 273893.69}, {"library": "Plympton Library", "distance": 414686.59, "duration": 333591.69, "weight": 269475}, {"library": "Plymstock Library", "distance": 419251.88, "duration": 336878.69, "weight": 272282.84}, {"library": "Southway Library", "distance": 419305, "duration": 336916.97, "weight": 271816.97}, {"library": "St Budeaux Library", "distance": 425642.75, "duration": 341480.13, "weight": 275980.97}, {"library": "West Park Library", "distance": 423865.38, "duration": 340200.44, "weight": 274666.47}]