[{"library": "Central Library", "distance": 616217.13, "duration": 22427.46, "weight": 22639.32}, {"library": "Crownhill Library", "distance": 613418.19, "duration": 22329.38, "weight": 22541.22}, {"library": "Devonport Library", "distance": 617275.81, "duration": 22529.04, "weight": 22740.9}, {"library": "Efford Library", "distance": 612361.81, "duration": 22467.19, "weight": 22679.03}, {"library": "Estover Library", "distance": 612719.25, "duration": 22260.67, "weight": 22472.51}, {"library": "North Prospect Library", "distance": 615566.69, "duration": 22381.17, "weight": 22593.02}, {"library": "Peverell Library", "distance": 613784.69, "duration": 22227.71, "weight": 22439.55}, {"library": "Plympton Library", "distance": 606774.13, "duration": 22087.3, "weight": 22299.14}, {"library": "Plymstock Library", "distance": 614076.81, "duration": 22446.56, "weight": 22658.41}, {"library": "Southway Library", "distance": 617412.5, "duration": 22474.49, "weight": 22686.34}, {"library": "St Budeaux Library", "distance": 617215.69, "duration": 22324.01, "weight": 22535.85}, {"library": "West Park Library", "distance": 617407, "duration": 22369.92, "weight": 22581.76}]