[{"library": "Central Library", "distance": 385898.56, "duration": 14519.92, "weight": 14512.2}, {"library": "Crownhill Library", "distance": 383099.63, "duration": 14421.84, "weight": 14414.1}, {"library": "Devonport Library", "distance": 386957.25, "duration": 14621.5, "weight": 14613.78}, {"library": "Efford Library", "distance": 382043.25, "duration": 14559.64, "weight": 14551.91}, {"library": "Estover Library", "distance": 382400.66, "duration": 14353.13, "weight": 14345.39}, {"library": "North Prospect Library", "distance": 385248.09, "duration": 14473.63, "weight": 14465.9}, {"library": "Peverell Library", "distance": 383466.13, "duration": 14320.17, "weight": 14312.43}, {"library": "Plympton Library", "distance": 376455.56, "duration": 14179.76, "weight": 14172.02}, {"library": "Plymstock Library", "distance": 383758.25, "duration": 14539.02, "weight": 14531.29}, {"library": "Southway Library", "distance": 387093.91, "duration": 14566.95, "weight": 14559.22}, {"library": "St Budeaux Library", "distance": 386897.13, "duration": 14416.47, "weight": 14408.73}, {"library": "West Park Library", "distance": 387088.44, "duration": 14462.38, "weight": 14454.64}]