[{"library": "Central Library", "distance": 476700.81, "duration": 344309.75, "weight": 312667.56}, {"library": "Crownhill Library", "distance": 475726.94, "duration": 343608.59, "weight": 311938.47}, {"library": "Devonport Library", "distance": 478903.41, "duration": 345895.59, "weight": 313963.28}, {"library": "Efford Library", "distance": 473695.88, "duration": 342146.22, "weight": 310719.31}, {"library": "Estover Library", "distance": 473683.72, "duration": 342137.47, "weight": 310804.25}, {"library": "North Prospect Library", "distance": 478127.09, "duration": 345336.69, "weight": 313340.47}, {"library": "Peverell Library", "distance": 476321.25, "duration": 344036.47, "weight": 312255.06}, {"library": "Plympton Library", "distance": 469328.03, "duration": 339001.41, "weight": 307836.38}, {"library": "Plymstock Library", "distance": 473893.31, "duration": 342288.38, "weight": 310644.22}, {"library": "Southway Library", "distance": 473946.41, "duration": 342326.69, "weight": 310178.34}, {"library": "St Budeaux Library", "distance": 480284.16, "duration": 346889.81, "weight": 314342.34}, {"library": "West Park Library", "distance": 478506.81, "duration": 345610.13, "weight": 313027.84}]