[{"library": "Central Library", "distance": 258706.33, "duration": 9301.3, "weight": 10142.55}, {"library": "Crownhill Library", "distance": 255907.41, "duration": 9203.22, "weight": 10044.45}, {"library": "Devonport Library", "distance": 259765.03, "duration": 9402.88, "weight": 10244.12}, {"library": "Efford Library", "distance": 254851.03, "duration": 9341.03, "weight": 10182.25}, {"library": "Estover Library", "distance": 255208.42, "duration": 9134.51, "weight": 9975.73}, {"library": "North Prospect Library", "distance": 258055.88, "duration": 9255.01, "weight": 10096.24}, {"library": "Peverell Library", "distance": 256273.91, "duration": 9101.55, "weight": 9942.77}, {"library": "Plympton Library", "distance": 249263.33, "duration": 8961.14, "weight": 9802.37}, {"library": "Plymstock Library", "distance": 256566.02, "duration": 9320.4, "weight": 10161.64}, {"library": "Southway Library", "distance": 259901.67, "duration": 9348.33, "weight": 10189.57}, {"library": "St Budeaux Library", "distance": 259704.89, "duration": 9197.85, "weight": 10039.08}, {"library": "West Park Library", "distance": 259896.2, "duration": 9243.76, "weight": 10084.99}]