[{"library": "Central Library", "distance": 550680.69, "duration": 129421.09, "weight": 97635.02}, {"library": "Crownhill Library", "distance": 564323.19, "duration": 131600.95, "weight": 97046.52}, {"library": "Devonport Library", "distance": 553569.19, "duration": 130091.2, "weight": 98179.3}, {"library": "Efford Library", "distance": 548478.25, "duration": 129062.82, "weight": 97390.74}, {"library": "Estover Library", "distance": 564044.81, "duration": 131457.95, "weight": 96847.85}, {"library": "North Prospect Library", "distance": 567654.63, "duration": 132357.38, "weight": 97816.9}, {"library": "Peverell Library", "distance": 566115.38, "duration": 132037.86, "weight": 97578.97}, {"library": "Plympton Library", "distance": 541851.75, "duration": 127361.13, "weight": 96010.8}, {"library": "Plymstock Library", "distance": 545382.5, "duration": 128138.57, "weight": 96749.24}, {"library": "Southway Library", "distance": 561768.63, "duration": 131037.8, "weight": 96375.35}, {"library": "St Budeaux Library", "distance": 566300.13, "duration": 132563.88, "weight": 97708.27}, {"library": "West Park Library", "distance": 565149.75, "duration": 132263.06, "weight": 97439.51}]