[{"library": "Central Library", "distance": 248361.16, "duration": 156898.13, "weight": 163172}, {"library": "Crownhill Library", "distance": 247786.81, "duration": 156484.67, "weight": 161968.92}, {"library": "Devonport Library", "distance": 250563.73, "duration": 158483.95, "weight": 164467.72}, {"library": "Efford Library", "distance": 245356.2, "duration": 154734.59, "weight": 161223.75}, {"library": "Estover Library", "distance": 245344.05, "duration": 154725.86, "weight": 161308.69}, {"library": "North Prospect Library", "distance": 249787.42, "duration": 157925.05, "weight": 163844.91}, {"library": "Peverell Library", "distance": 247981.58, "duration": 156624.84, "weight": 162759.52}, {"library": "Plympton Library", "distance": 240988.38, "duration": 151589.78, "weight": 158340.81}, {"library": "Plymstock Library", "distance": 245553.66, "duration": 154876.77, "weight": 161148.67}, {"library": "Southway Library", "distance": 245432.28, "duration": 154789.44, "weight": 160082.81}, {"library": "St Budeaux Library", "distance": 251770.03, "duration": 159352.58, "weight": 164246.81}, {"library": "West Park Library", "distance": 249992.67, "duration": 158072.89, "weight": 162932.31}]