[{"library": "Central Library", "distance": 216916.14, "duration": 8039.58, "weight": 8039.76}, {"library": "Crownhill Library", "distance": 214117.22, "duration": 7941.5, "weight": 7941.66}, {"library": "Devonport Library", "distance": 217974.84, "duration": 8141.15, "weight": 8141.33}, {"library": "Efford Library", "distance": 213060.84, "duration": 8079.3, "weight": 8079.46}, {"library": "Estover Library", "distance": 213418.25, "duration": 7872.78, "weight": 7872.95}, {"library": "North Prospect Library", "distance": 216265.69, "duration": 7993.29, "weight": 7993.45}, {"library": "Peverell Library", "distance": 214483.73, "duration": 7839.83, "weight": 7839.98}, {"library": "Plympton Library", "distance": 207473.14, "duration": 7699.41, "weight": 7699.58}, {"library": "Plymstock Library", "distance": 214775.83, "duration": 8058.68, "weight": 8058.85}, {"library": "Southway Library", "distance": 218111.48, "duration": 8086.6, "weight": 8086.78}, {"library": "St Budeaux Library", "distance": 217914.7, "duration": 7936.13, "weight": 7936.29}, {"library": "West Park Library", "distance": 218106.02, "duration": 7982.03, "weight": 7982.2}]