[{"library": "Central Library", "distance": 332435.47, "duration": 67173.02, "weight": 61025.06}, {"library": "Crownhill Library", "distance": 346078, "duration": 69352.88, "weight": 60436.55}, {"library": "Devonport Library", "distance": 335323.97, "duration": 67843.13, "weight": 61569.33}, {"library": "Efford Library", "distance": 330233.03, "duration": 66814.75, "weight": 60780.78}, {"library": "Estover Library", "distance": 345799.63, "duration": 69209.88, "weight": 60237.89}, {"library": "North Prospect Library", "distance": 349409.41, "duration": 70109.3, "weight": 61206.94}, {"library": "Peverell Library", "distance": 347870.16, "duration": 69789.79, "weight": 60969.01}, {"library": "Plympton Library", "distance": 323606.53, "duration": 65113.05, "weight": 59400.84}, {"library": "Plymstock Library", "distance": 327137.28, "duration": 65890.5, "weight": 60139.28}, {"library": "Southway Library", "distance": 343523.41, "duration": 68789.73, "weight": 59765.39}, {"library": "St Budeaux Library", "distance": 348054.94, "duration": 70315.8, "weight": 61098.3}, {"library": "West Park Library", "distance": 346904.56, "duration": 70014.99, "weight": 60829.54}]